Workbook

Sheet Dashboard
A1: MONTHLY EXPENSE TRACKER & FINANCIAL SUMMARY
A3: Month & Year: | B3: June 2026
A5: INCOME INFORMATION
A6: Gross Monthly Income: | B6: 125000
A7: Other Income: | B7: 0
A8: Total Income: | B8: =B6+B7 -> 125000
A10: EXPENSE SUMMARY
A11: Total Fixed Expenses: | B11: =SUMIF(Expenses!$D:$D,"Fixed",Expenses!$E:$E) -> 46800
A12: Total Variable Expenses: | B12: =SUMIF(Expenses!$D:$D,"Variable",Expenses!$E:$E) -> 18200
A13: Total Monthly Expenses: | B13: =B11+B12 -> 65000
A15: FINANCIAL SUMMARY
A16: Total Savings: | B16: =B8-B13 -> 60000
A17: Savings Rate (%): | B17: =IF(B8=0,0,B16/B8) -> 0.48
A18: Remaining Balance: | B18: =B16 -> 60000
A20: CATEGORY-WISE EXPENSE BREAKDOWN
A21: Home Loan EMI | B21: =SUMIF(Expenses!$B:$B,A21,Expenses!$E:$E) -> 22000
A22: Personal Loan EMI2
A23: Personal Loan EMI | B23: =SUMIF(Expenses!$B:$B,A23,Expenses!$E:$E) -> 23000
A24: Car Loan EMI | B24: =SUMIF(Expenses!$B:$B,A24,Expenses!$E:$E) -> 0
A25: Parking Charges | B25: =SUMIF(Expenses!$B:$B,A25,Expenses!$E:$E) -> 15000
A26: Groceries | B26: =SUMIF(Expenses!$B:$B,A26,Expenses!$E:$E) -> 2000
A27: Gym Membership | B27: =SUMIF(Expenses!$B:$B,A27,Expenses!$E:$E) -> 0
A28: Home Needs | B28: =SUMIF(Expenses!$B:$B,A28,Expenses!$E:$E) -> 0
A29: Personal Expenses | B29: =SUMIF(Expenses!$B:$B,A29,Expenses!$E:$E) -> 600
A30: Electricity Bill | B30: =SUMIF(Expenses!$B:$B,A30,Expenses!$E:$E) -> 1800
A31: Water Bill | B31: =SUMIF(Expenses!$B:$B,A31,Expenses!$E:$E) -> 0
A32: Gas Bill | B32: =SUMIF(Expenses!$B:$B,A32,Expenses!$E:$E) -> 0
A33: Internet/Broadband | B33: =SUMIF(Expenses!$B:$B,A33,Expenses!$E:$E) -> 0
A34: Mobile Recharge | B34: =SUMIF(Expenses!$B:$B,A34,Expenses!$E:$E) -> 0
... A42: Miscellaneous | B42: =SUMIF(Expenses!$B:$B,A42,Expenses!$E:$E) -> 0

Sheet Expenses
A1: Date | B1: Personal Loan EMI | C1: Description | D1: Type | E1: Amount | F1: Payment Method | G1: Notes
A2: 01-06-2026 | B2: Home Loan EMI | C2: Home Loan - Monthly EMI | D2: Fixed | E2: 22000 | F2: Bank Account | G2: Principal + Interest
A3: 02-06-2026 | B3: Groceries | C3: Weekly Grocery Shopping | D3: Variable | E3: 2000 | F3: UPI | G3: Vegetables, fruits, dairy
A4: 02-06-2026 | B4: Electricity Bill | C4: June Electricity Bill | D4: Fixed | E4: 1800 | F4: Bank Account | G4: Monthly utility
A5: 03-06-2026 | B5: Personal Loan EMI | C5: Personal Loan EMI | D5: Fixed | E5: 23000 | F5: Bank Account | G5: Personal loan installment
A6: 28-06-2026 | B6: Personal Expenses | C6: Entertainment tickets | D6: Variable | E6: 600 | F6: Credit Card | G6: Movie tickets
A7: 29-06-2026 | B7: Transportation | C7: Local travel | D7: Variable | E7: 200 | F7: Cash | G7: Daily commute
A8: 30-06-2026 | B8: Dining Out | C8: Casual lunch | D8: Variable | E8: 400 | F8: UPI | G8: Quick lunch
B9: Parking Charges | E9: 15000
A10: 29-06-2026 | B10: Personal Loan EMI2 | C10: Local travel | D10: Variable | E10: 15000 | F10: Cash | G10: Daily commute
A11: 30-06-2026 | C11: Casual lunch | D11: Variable | F11: UPI | G11: Quick lunch

Sheet Monthly Summary
A1: MONTHLY EXPENSE REPORT
A3: EXPENSE SUMMARY BY TYPE
A4: Expense Type | B4: Amount | C4: % of Total
A5: Fixed Expenses | B5: =SUMIF(Expenses!$D:$D,"Fixed",Expenses!$E:$E) -> 46800 | C5: =IF(SUM(B5:B6)=0,0,B5/SUM(B5:B6)) -> 0.72
A6: Variable Expenses | B6: =SUMIF(Expenses!$D:$D,"Variable",Expenses!$E:$E) -> 18200 | C6: =IF(SUM(B5:B6)=0,0,B6/SUM(B5:B6)) -> 0.28
A7: Total Expenses | B7: =SUM(B5:B6) -> 65000
A9: EMI SUMMARY
A10: EMI Type | B10: Amount
A11: Home Loan EMI | B11: =SUMIF(Expenses!$B:$B,A11,Expenses!$E:$E) -> 22000
A12: Personal Loan EMI | B12: =SUMIF(Expenses!$B:$B,A12,Expenses!$E:$E) -> 23000
A13: Car Loan EMI | B13: =SUMIF(Expenses!$B:$B,A13,Expenses!$E:$E) -> 0
A14: Total EMI Payments | B14: =SUM(B11:B13) -> 45000
A16: UTILITY BILLS SUMMARY
A17: Utility | B17: Amount
A18: Electricity Bill | B18: =SUMIF(Expenses!$B:$B,A18,Expenses!$E:$E) -> 1800
A19: Water Bill | B19: =SUMIF(Expenses!$B:$B,A19,Expenses!$E:$E) -> 0
A20: Gas Bill | B20: =SUMIF(Expenses!$B:$B,A20,Expenses!$E:$E) -> 0
A21: Internet/Broadband | B21: =SUMIF(Expenses!$B:$B,A21,Expenses!$E:$E) -> 0
A22: Mobile Recharge | B22: =SUMIF(Expenses!$B:$B,A22,Expenses!$E:$E) -> 0
A23: Total Utility Bills | B23: =SUM(B18:B22) -> 1800

Sheet Instructions
A2: STEP 1: Dashboard Setup
A3: 1. Go to the "Dashboard" sheet
A4: 2. Enter the Month & Year in cell B3
A5: 3. Enter your Gross Monthly Income in cell B6
A6: 4. Enter any Other Income in cell B7
A8: STEP 2: Add Expenses
A9: 1. Go to the "Expenses" sheet
A10: 2. In each row, enter:
A11: • Date (in dd-mm-yyyy format)
A12: • Category (dropdown list available)
A13: • Description of the expense
A14: • Type: Fixed or Variable (dropdown)
... A43: • Create a new sheet for each month by copying the Expenses sheet
